llama_index/tools/arxiv/__init__.py
llama_index/tools/arxiv/base.py
llama_index_tools_arxiv-0.4.1.dist-info/METADATA
llama_index_tools_arxiv-0.4.1.dist-info/WHEEL
llama_index_tools_arxiv-0.4.1.dist-info/licenses/LICENSE
llama_index_tools_arxiv-0.4.1.dist-info/RECORD
