Metadata-Version: 2.4
Name: llama-index-tools-arxiv
Version: 0.4.1
Summary: llama-index tools arxiv integration
Author-email: Your Name <you@example.com>
Maintainer: ajhofmann
License-Expression: MIT
License-File: LICENSE
Keywords: math,research,science
Requires-Python: <4.0,>=3.9
Requires-Dist: arxiv<3,>=2.1.0
Requires-Dist: llama-index-core<0.15,>=0.13.0
